brci/.env
brci/.perf.test.env
brci/Dockerfile-online-compile
brci/__init__.py
brci/bm_supa_perf_cur_test.csv
brci/bm_supa_perf_cur_test2.csv
brci/compare.conf.template
brci/createPod.py
brci/report03.csv
brci/requirements.txt
brci/run.py
brci/temp_last.csv
brci/test_hander_perf.py
brci/test_pod.yml
brci/__pycache__/__init__.cpython-39.pyc
brci/__pycache__/createPod.cpython-39.pyc
brci/__pycache__/main.cpython-39.pyc
brci/__pycache__/run.cpython-39.pyc
brci/apis/__init__.py
brci/apis/build.py
brci/apis/client.py
brci/apis/pdu.py
brci/apis/perf.py
brci/apis/pr.py
brci/apis/__pycache__/__init__.cpython-39.pyc
brci/apis/__pycache__/build.cpython-39.pyc
brci/apis/__pycache__/client.cpython-39.pyc
brci/apis/__pycache__/pdu.cpython-39.pyc
brci/apis/__pycache__/perf.cpython-39.pyc
brci/apis/__pycache__/pr.cpython-39.pyc
brci/config/__init__.py
brci/config/develop.py
brci/config/prod.py
brci/config/__pycache__/__init__.cpython-39.pyc
brci/config/__pycache__/develop.cpython-39.pyc
brci/handles/__init__.py
brci/handles/build.py
brci/handles/pdu.py
brci/handles/perf.py
brci/handles/pr.py
brci/handles/repo.py
brci/handles/__pycache__/__init__.cpython-39.pyc
brci/handles/__pycache__/build.cpython-39.pyc
brci/handles/__pycache__/pdu.cpython-39.pyc
brci/handles/__pycache__/perf.cpython-39.pyc
brci/handles/__pycache__/pr.cpython-39.pyc
brci/handles/__pycache__/repo.cpython-39.pyc
brci/schemas/__init__.py
brci/schemas/jenkins.py
brci/schemas/pull_request.py
brci/schemas/pull_request_job.py
brci/schemas/test_case.py
brci/schemas/__pycache__/__init__.cpython-39.pyc
brci/schemas/__pycache__/jenkins.cpython-39.pyc
brci/schemas/__pycache__/pull_request.cpython-39.pyc
brci/schemas/__pycache__/pull_request_job.cpython-39.pyc
brci/schemas/__pycache__/test_case.cpython-39.pyc
brci/utils/__init__.py
brci/utils/csv_utils.py
brci/utils/file_utils.py
brci/utils/json_utils.py
brci/utils/pd_utils.py
brci/utils/xml_utils.py
brci/utils/__pycache__/__init__.cpython-39.pyc
br_ci_sdk-0.0.3.dist-info/METADATA
br_ci_sdk-0.0.3.dist-info/WHEEL
br_ci_sdk-0.0.3.dist-info/entry_points.txt
br_ci_sdk-0.0.3.dist-info/top_level.txt
br_ci_sdk-0.0.3.dist-info/RECORD
